tmap/__init__.py
tmap/api/Network_generator.py
tmap/api/SAFE_analysis.py
tmap/api/SAFE_visualization.py
tmap/api/__init__.py
tmap/api/envfit_analysis.py
tmap/api/general.py
tmap/netx/SAFE.py
tmap/netx/__init__.py
tmap/netx/coenrichment_analysis.py
tmap/netx/driver_detect_beta.py
tmap/tda/Filter.py
tmap/tda/__init__.py
tmap/tda/basic.py
tmap/tda/cover.py
tmap/tda/graph.py
tmap/tda/mapper.py
tmap/tda/metric.py
tmap/tda/plot.py
tmap/tda/utils.py
tmap/test/__init__.py
tmap/test/load_data.py
tmap/test/test_Daily_saliva.py
tmap/test/test_Daily_stool.py
tmap/test/test_FGFP.py
tmap/test/test_circles.py
tmap/test/test_digits.py
tmap/test/test_iris.py
tmap/test/test_data/Daily_metadata.csv
tmap/test/test_data/Daily_saliva_genus.csv
tmap/test/test_data/Daily_stool_genus.csv
tmap/test/test_data/FGFP_bc_dm.csv
tmap/test/test_data/FGFP_genus_data.csv
tmap/test/test_data/FGFP_metadata.tsv
tmap/test/test_data/FGFP_metadata_ready.tsv
tmap-1.0.1.data/scripts/Network_generator.py
tmap-1.0.1.data/scripts/SAFE_analysis.py
tmap-1.0.1.data/scripts/SAFE_visualization.py
tmap-1.0.1.data/scripts/envfit_analysis.py
tmap-1.0.1.dist-info/LICENSE
tmap-1.0.1.dist-info/METADATA
tmap-1.0.1.dist-info/WHEEL
tmap-1.0.1.dist-info/top_level.txt
tmap-1.0.1.dist-info/RECORD
