Metadata-Version: 2.1
Name: tmap
Version: 1.0.1
Summary: A topological data analysis framework implementing the TDA Mapper algorithm for population-scale microbiome data analysis 
Home-page: https://github.com/GPZ-Bioinfo/tmap
Author: Haokui Zhou, Tianhua Liao
Author-email: zhouhaokui@hotmail.com
License: GNU
Platform: UNKNOWN
Classifier: Programming Language :: Python :: 3
Classifier: License :: OSI Approved :: GNU General Public License v3 (GPLv3)
Classifier: Operating System :: OS Independent
Classifier: Topic :: Scientific/Engineering :: Bio-Informatics
Requires-Dist: statsmodels (>=0.9.0)
Requires-Dist: tqdm
Requires-Dist: scikit-learn (>=0.19.1)
Requires-Dist: matplotlib (>=2.2.2)
Requires-Dist: networkx (>=2.1)
Requires-Dist: pandas (>=0.23.0)
Requires-Dist: scipy
Requires-Dist: matplotlib (!=3.0.0rc2)
Requires-Dist: umap-learn
Requires-Dist: scikit-bio (>=0.5.2)
Requires-Dist: numpy (<1.14.0,>=1.9.2)
Requires-Dist: rpy2
Requires-Dist: plotly
